py2vega/__init__.py
py2vega/constants.py
py2vega/main.py
py2vega/functions/__init__.py
py2vega/functions/array.py
py2vega/functions/color.py
py2vega/functions/date_time.py
py2vega/functions/formatting.py
py2vega/functions/math.py
py2vega/functions/object.py
py2vega/functions/regexp.py
py2vega/functions/scale.py
py2vega/functions/string.py
py2vega/functions/type_checking.py
py2vega/functions/type_coercing.py
py2vega-0.6.1.dist-info/LICENSE
py2vega-0.6.1.dist-info/METADATA
py2vega-0.6.1.dist-info/WHEEL
py2vega-0.6.1.dist-info/top_level.txt
py2vega-0.6.1.dist-info/RECORD
